galaxy/command/__init__.py
galaxy/command/cmd.py
galaxy/command/constant.py
galaxy/command/interpreter.py
galaxy/command/router.py
galaxy/command/sub.py
galaxy_py_cmd-0.0.9.dist-info/AUTHORS
galaxy_py_cmd-0.0.9.dist-info/COPYING.md
galaxy_py_cmd-0.0.9.dist-info/LICENSE.txt
galaxy_py_cmd-0.0.9.dist-info/METADATA
galaxy_py_cmd-0.0.9.dist-info/WHEEL
galaxy_py_cmd-0.0.9.dist-info/RECORD
