Metadata-Version: 2.3
Name: galaxy-py-cmd
Version: 0.0.9
Summary: Python Command for the Galaxy Project
License: Apache-2.0
Keywords: galaxy,galaxy-cmd
Author: Bastien Saltel
Author-email: bastien.saltel@gmail.com
Maintainer: Bastien Saltel
Maintainer-email: bastien.saltel@gmail.com
Requires-Python: >=3.10,<4.0
Classifier: Development Status :: 3 - Alpha
Classifier: Programming Language :: Python :: 3
Classifier: Operating System :: OS Independent
Requires-Dist: galaxy-py-app
Requires-Dist: galaxy-py-data
Requires-Dist: galaxy-py-error
Requires-Dist: galaxy-py-kernel
Requires-Dist: galaxy-py-net
Requires-Dist: galaxy-py-perfo
Requires-Dist: galaxy-py-service
Requires-Dist: galaxy-py-utils
Requires-Dist: pyyaml
Requires-Dist: reactivex
Project-URL: Changelog, https://github.com/bsaltel/galaxy-py-cmd/blob/main/CHANGELOG.md
Project-URL: Documentation, https://github.com/bsaltel/galaxy-py-cmd
Project-URL: Homepage, https://github.com/bsaltel/galaxy-py-cmd
Project-URL: Issues, https://github.com/bsaltel/galaxy-py-cmd/issues
Project-URL: Repository, https://github.com/bsaltel/galaxy-py-cmd.git
